naogi/__init__.py
naogi-0.0.6.dist-info/LICENSE
naogi-0.0.6.dist-info/METADATA
naogi-0.0.6.dist-info/WHEEL
naogi-0.0.6.dist-info/top_level.txt
naogi-0.0.6.dist-info/RECORD
